cognitiveatlas/__init__.py
cognitiveatlas/api.py
cognitiveatlas/datastructure.py
cognitiveatlas/utils.py
cognitiveatlas-0.1.11.dist-info/LICENSE.txt
cognitiveatlas-0.1.11.dist-info/METADATA
cognitiveatlas-0.1.11.dist-info/WHEEL
cognitiveatlas-0.1.11.dist-info/top_level.txt
cognitiveatlas-0.1.11.dist-info/RECORD
